eTestificatus/__init__.py
eTestificatus/eTestificatus.py
etestificatus-0.0.7.dist-info/LICENSE
etestificatus-0.0.7.dist-info/METADATA
etestificatus-0.0.7.dist-info/WHEEL
etestificatus-0.0.7.dist-info/top_level.txt
etestificatus-0.0.7.dist-info/RECORD
